{"key":"339_1263","cellSize":0.1,"count":7,"lots":[{"id":"PUBLIC_405-2-000362","name":"묵리 374","publicPrivateType":"공영","parkingType":"노외","roadAddress":"","jibunAddress":"제주특별자치도 제주시 추자면 묵리 374","address":"제주특별자치도 제주시 추자면 묵리 374","lat":33.9456663,"lng":126.3156068,"region":"제주","district":"제주시","capacity":6,"operatingDays":"평일+토요일+공휴일","weekdayOpen":"00:00","weekdayClose":"23:59","saturdayOpen":"00:00","saturdayClose":"23:59","holidayOpen":"00:00","holidayClose":"23:59","feeType":"무료","baseMinutes":0,"baseFee":0,"additionalMinutes":0,"additionalFee":0,"unitMinutes":0,"unitFee":0,"dayPassFee":null,"dailyMaxFee":null,"monthlyFee":null,"paymentMethods":"현장 확인","agencyName":"제주특별자치도 제주시청","phone":"","dataDate":"2026-04-16","sourceUpdatedAt":"2026-04-16","source":"공공데이터포털 전국주차장정보표준데이터","coordinateSource":"csv","geocoded":false,"pricingStatus":"free","realtimeAvailable":null,"realtimeKey":null,"disabledDiscountRate":50,"compactDiscountRate":50,"evDiscountRate":50},{"id":"PUBLIC_405-2-000361","name":"예초리 266","publicPrivateType":"공영","parkingType":"노외","roadAddress":"","jibunAddress":"제주특별자치도 제주시 추자면 예초리 266","address":"제주특별자치도 제주시 추자면 예초리 266","lat":33.9541396,"lng":126.332782,"region":"제주","district":"제주시","capacity":7,"operatingDays":"평일+토요일+공휴일","weekdayOpen":"00:00","weekdayClose":"23:59","saturdayOpen":"00:00","saturdayClose":"23:59","holidayOpen":"00:00","holidayClose":"23:59","feeType":"무료","baseMinutes":0,"baseFee":0,"additionalMinutes":0,"additionalFee":0,"unitMinutes":0,"unitFee":0,"dayPassFee":null,"dailyMaxFee":null,"monthlyFee":null,"paymentMethods":"현장 확인","agencyName":"제주특별자치도 제주시청","phone":"","dataDate":"2026-04-16","sourceUpdatedAt":"2026-04-16","source":"공공데이터포털 전국주차장정보표준데이터","coordinateSource":"csv","geocoded":false,"pricingStatus":"free","realtimeAvailable":null,"realtimeKey":null,"disabledDiscountRate":50,"compactDiscountRate":50,"evDiscountRate":50},{"id":"PUBLIC_405-2-000359","name":"신양리 782, 783-4","publicPrivateType":"공영","parkingType":"노외","roadAddress":"","jibunAddress":"제주특별자치도 제주시 추자면 신양리 782","address":"제주특별자치도 제주시 추자면 신양리 782","lat":33.9414307,"lng":126.3197854,"region":"제주","district":"제주시","capacity":13,"operatingDays":"평일+토요일+공휴일","weekdayOpen":"00:00","weekdayClose":"23:59","saturdayOpen":"00:00","saturdayClose":"23:59","holidayOpen":"00:00","holidayClose":"23:59","feeType":"무료","baseMinutes":0,"baseFee":0,"additionalMinutes":0,"additionalFee":0,"unitMinutes":0,"unitFee":0,"dayPassFee":null,"dailyMaxFee":null,"monthlyFee":null,"paymentMethods":"현장 확인","agencyName":"제주특별자치도 제주시청","phone":"","dataDate":"2026-04-16","sourceUpdatedAt":"2026-04-16","source":"공공데이터포털 전국주차장정보표준데이터","coordinateSource":"csv","geocoded":false,"pricingStatus":"free","realtimeAvailable":null,"realtimeKey":null,"disabledDiscountRate":50,"compactDiscountRate":50,"evDiscountRate":50},{"id":"PUBLIC_405-2-000357","name":"신양리 817-1","publicPrivateType":"공영","parkingType":"노외","roadAddress":"","jibunAddress":"제주특별자치도 제주시 추자면 신양리 817-1","address":"제주특별자치도 제주시 추자면 신양리 817-1","lat":33.9412107,"lng":126.3211742,"region":"제주","district":"제주시","capacity":6,"operatingDays":"평일+토요일+공휴일","weekdayOpen":"00:00","weekdayClose":"23:59","saturdayOpen":"00:00","saturdayClose":"23:59","holidayOpen":"00:00","holidayClose":"23:59","feeType":"무료","baseMinutes":0,"baseFee":0,"additionalMinutes":0,"additionalFee":0,"unitMinutes":0,"unitFee":0,"dayPassFee":null,"dailyMaxFee":null,"monthlyFee":null,"paymentMethods":"현장 확인","agencyName":"제주특별자치도 제주시청","phone":"","dataDate":"2026-04-16","sourceUpdatedAt":"2026-04-16","source":"공공데이터포털 전국주차장정보표준데이터","coordinateSource":"csv","geocoded":false,"pricingStatus":"free","realtimeAvailable":null,"realtimeKey":null,"disabledDiscountRate":50,"compactDiscountRate":50,"evDiscountRate":50},{"id":"PUBLIC_405-2-000355","name":"신양리 610-1","publicPrivateType":"공영","parkingType":"노외","roadAddress":"","jibunAddress":"제주특별자치도 제주시 추자면 신양리 610-1","address":"제주특별자치도 제주시 추자면 신양리 610-1","lat":33.9429478,"lng":126.3214614,"region":"제주","district":"제주시","capacity":3,"operatingDays":"평일+토요일+공휴일","weekdayOpen":"00:00","weekdayClose":"23:59","saturdayOpen":"00:00","saturdayClose":"23:59","holidayOpen":"00:00","holidayClose":"23:59","feeType":"무료","baseMinutes":0,"baseFee":0,"additionalMinutes":0,"additionalFee":0,"unitMinutes":0,"unitFee":0,"dayPassFee":null,"dailyMaxFee":null,"monthlyFee":null,"paymentMethods":"현장 확인","agencyName":"제주특별자치도 제주시청","phone":"","dataDate":"2026-04-16","sourceUpdatedAt":"2026-04-16","source":"공공데이터포털 전국주차장정보표준데이터","coordinateSource":"csv","geocoded":false,"pricingStatus":"free","realtimeAvailable":null,"realtimeKey":null,"disabledDiscountRate":50,"compactDiscountRate":50,"evDiscountRate":50},{"id":"PUBLIC_405-2-000353","name":"예초리 215-1","publicPrivateType":"공영","parkingType":"노외","roadAddress":"","jibunAddress":"제주특별자치도 제주시 추자면 예초리 215-1","address":"제주특별자치도 제주시 추자면 예초리 215-1","lat":33.955008,"lng":126.3336059,"region":"제주","district":"제주시","capacity":4,"operatingDays":"평일+토요일+공휴일","weekdayOpen":"00:00","weekdayClose":"23:59","saturdayOpen":"00:00","saturdayClose":"23:59","holidayOpen":"00:00","holidayClose":"23:59","feeType":"무료","baseMinutes":0,"baseFee":0,"additionalMinutes":0,"additionalFee":0,"unitMinutes":0,"unitFee":0,"dayPassFee":null,"dailyMaxFee":null,"monthlyFee":null,"paymentMethods":"현장 확인","agencyName":"제주특별자치도 제주시청","phone":"","dataDate":"2026-04-16","sourceUpdatedAt":"2026-04-16","source":"공공데이터포털 전국주차장정보표준데이터","coordinateSource":"csv","geocoded":false,"pricingStatus":"free","realtimeAvailable":null,"realtimeKey":null,"disabledDiscountRate":50,"compactDiscountRate":50,"evDiscountRate":50},{"id":"PUBLIC_405-2-000349","name":"신양리 434-10","publicPrivateType":"공영","parkingType":"노외","roadAddress":"","jibunAddress":"제주특별자치도 제주시 추자면 신양리 434-10","address":"제주특별자치도 제주시 추자면 신양리 434-10","lat":33.9449884,"lng":126.3288633,"region":"제주","district":"제주시","capacity":30,"operatingDays":"평일+토요일+공휴일","weekdayOpen":"00:00","weekdayClose":"23:59","saturdayOpen":"00:00","saturdayClose":"23:59","holidayOpen":"00:00","holidayClose":"23:59","feeType":"무료","baseMinutes":0,"baseFee":0,"additionalMinutes":0,"additionalFee":0,"unitMinutes":0,"unitFee":0,"dayPassFee":null,"dailyMaxFee":null,"monthlyFee":null,"paymentMethods":"현장 확인","agencyName":"제주특별자치도 제주시청","phone":"","dataDate":"2026-04-16","sourceUpdatedAt":"2026-04-16","source":"공공데이터포털 전국주차장정보표준데이터","coordinateSource":"csv","geocoded":false,"pricingStatus":"free","realtimeAvailable":null,"realtimeKey":null,"disabledDiscountRate":50,"compactDiscountRate":50,"evDiscountRate":50}]}